README.rst
setup.cfg
setup.py
src/django_nap.egg-info/PKG-INFO
src/django_nap.egg-info/SOURCES.txt
src/django_nap.egg-info/dependency_links.txt
src/django_nap.egg-info/not-zip-safe
src/django_nap.egg-info/requires.txt
src/django_nap.egg-info/top_level.txt
src/nap/__init__.py
src/nap/shortcuts.py
src/nap/extras/__init__.py
src/nap/extras/actions.py
src/nap/extras/simplecsv.py
src/nap/http/__init__.py
src/nap/http/decorators.py
src/nap/http/response.py
src/nap/mapper/__init__.py
src/nap/mapper/base.py
src/nap/mapper/fields.py
src/nap/mapper/models.py
src/nap/mapper/utils.py
src/nap/rest/__init__.py
src/nap/rest/views/__init__.py
src/nap/rest/views/base.py
src/nap/rest/views/list.py
src/nap/rest/views/object.py
src/nap/rpc/__init__.py
src/nap/rpc/client.py
src/nap/rpc/views.py
src/nap/utils/__init__.py
src/nap/utils/ripper.py