Metadata-Version: 2.1
Name: django-nap
Version: 0.40.0
Summary: A light REST tool for Django
Home-page: http://github.com/funkybob/django-nap
Author: Curtis Maloney
Author-email: curtis@tinbrain.net
License: UNKNOWN
Keywords: django,json,rest,api
Platform: UNKNOWN
Classifier: Environment :: Web Environment
Classifier: Framework :: Django
Classifier: License :: OSI Approved :: BSD License
Classifier: Operating System :: OS Independent
Classifier: Programming Language :: Python
Classifier: Programming Language :: Python :: 3.4
Classifier: Programming Language :: Python :: 3.5
Classifier: Programming Language :: Python :: 3.6
Requires: Django (>=2.0)
Provides-Extra: rps
